asyncflows_classify/__init__.py
asyncflows_classify/actions/__init__.py
asyncflows_classify/actions/classify.py
asyncflows_classify/actions/extract.py
asyncflows_classify/tests/__init__.py
asyncflows_classify/tests/conftest.py
asyncflows_classify/tests/test_classify.py
asyncflows_classify/tests/test_extract.py
asyncflows_classify/utils.py
asyncflows_classify-0.1.2.dist-info/METADATA
asyncflows_classify-0.1.2.dist-info/WHEEL
asyncflows_classify-0.1.2.dist-info/entry_points.txt
asyncflows_classify-0.1.2.dist-info/RECORD
