Metadata-Version: 2.1
Name: asyncflows-classify
Version: 0.1.2
Summary: 
Author: Rafael Irgolic
Author-email: hello@irgolic.com
Requires-Python: >=3.10,<3.12
Classifier: Programming Language :: Python :: 3
Classifier: Programming Language :: Python :: 3.10
Classifier: Programming Language :: Python :: 3.11
Requires-Dist: asyncflows (>=0.1.10)
